r2d2.py
r2d2-3.0.0.dist-info/LICENSE
r2d2-3.0.0.dist-info/METADATA
r2d2-3.0.0.dist-info/WHEEL
r2d2-3.0.0.dist-info/top_level.txt
r2d2-3.0.0.dist-info/RECORD
