Metadata-Version: 2.1
Name: r2d2
Version: 3.0.0
Summary: some handy functions
Home-page: https://github.com/clumsyme/r2d2
Author: Li Yan
Author-email: me@imliyan.com
License: MIT
Platform: UNKNOWN
Classifier: License :: OSI Approved :: MIT License
Classifier: Programming Language :: Python
Classifier: Programming Language :: Python :: 3.6
Classifier: Programming Language :: Python :: Implementation :: CPython
Classifier: Programming Language :: Python :: Implementation :: PyPy
Requires-Python: >=3.6.0
